Module/__init__.py
databased_beta-0.0.1.dist-info/METADATA
databased_beta-0.0.1.dist-info/WHEEL
databased_beta-0.0.1.dist-info/top_level.txt
databased_beta-0.0.1.dist-info/RECORD
