Metadata-Version: 2.1
Name: databased-beta
Version: 0.0.1
Summary: This is the simplest module for quick work with databases.
Home-page: https://github.com/UserSal1/
Author: Romaska555
Author-email: example@gmail.com
Project-URL: GitHub, https://github.com/UserSal1/
Keywords: files speedfiles
Classifier: Programming Language :: Python :: 3.12
Classifier: License :: OSI Approved :: MIT License
Classifier: Operating System :: OS Independent
Requires-Python: >=3.6
Requires-Dist: requests >=2.25.1
